{
    "test": {
        "name": "Test",
        "race": "Human",
        "gender": "Male",
        "age": 38,
        "origin": "Test 2",
        "description": "",
        "traits": [],
        "characteristics": {
            "FOR": {
                "value": 5,
                "modifier": -1
            },
            "DES": {
                "value": 6,
                "modifier": 0
            },
            "RES": {
                "value": 7,
                "modifier": 0
            },
            "PSI": {
                "value": 0,
                "modifier": 0
            },
            "INT": {
                "value": 8,
                "modifier": 0
            },
            "EDU": {
                "value": 8,
                "modifier": 0
            },
            "SOC": {
                "value": 12,
                "modifier": 2
            },
            "PPU": "56788C"
        },
        "injuries": {
            "FOR": "",
            "DES": "",
            "RES": "",
            "armor": "",
            "VA": ""
        },
        "abilities": {
            "Computer": 1,
            "Linguistic": 0,
            "Space Sciences": 0,
            "Administration": 0,
            "Street Law": 1,
            "Corruption": 1,
            "Leadership": 0,
            "Vehicles": 0,
            "Connection": 0,
            "Survival": 0
        },
        "goods": [
            "Lower Passage"
        ],
        "credits": 450,
        "equipment": [
            "Model 1",
            "comunicators",
            "Mid Range Comunicator",
            "Geiger Counter"
        ],
        "careers": {
            "1": {
                "name": "Commisioned Special Agent",
                "grade": 2,
                "conscription_flag": 0,
                "service_periods": 1
            },
            "2": {
                "name": "",
                "grade": 0,
                "conscription_flag": "",
                "service_periods": 0
            },
            "3": {
                "name": "",
                "grade": 0,
                "conscription_flag": "",
                "service_periods": 0
            },
            "4": {
                "name": "",
                "grade": 0,
                "conscription_flag": "",
                "service_periods": 0
            },
            "5": {
                "name": "",
                "grade": 0,
                "conscription_flag": "",
                "service_periods": 0
            },
            "6": {
                "name": "",
                "grade": 0,
                "conscription_flag": "",
                "service_periods": 0
            },
            "7": {
                "name": "",
                "grade": 0,
                "conscription_flag": "",
                "service_periods": 0
            }
        }
    }
}